iron/__init__.py
iron/cli.py
iron/commands.py
iron/core.py
iron/decorators.py
iron/exceptions.py
iron/io.py
iron/local.py
iron/registry.py
iron/runtime.py
iron/utils.py
iron/watchers.py
iron/lib/__init__.py
iron/lib/_helpers.py
iron/lib/angular.py
iron/lib/basics.py
iron/lib/css.py
iron/lib/filters.py
iron/lib/gzip.py
iron/lib/html.py
iron/lib/io.py
iron/lib/javascript.py
iron/lib/markdown.py
iron/lib/paths.py
iron/lib/png.py
iron/lib/templating.py
iron/lib/text.py
iron/lib/textile.py
iron/lib/web.py
iron-0.3.0.dist-info/DESCRIPTION.rst
iron-0.3.0.dist-info/entry_points.txt
iron-0.3.0.dist-info/METADATA
iron-0.3.0.dist-info/metadata.json
iron-0.3.0.dist-info/RECORD
iron-0.3.0.dist-info/top_level.txt
iron-0.3.0.dist-info/WHEEL
