Metadata-Version: 2.0
Name: iron
Version: 0.3.0
Summary: iron: the powerful but simple build tool using flows.
Home-page: https://github.com/nvie/iron
Author: Vincent Driessen
Author-email: me@nvie.com
License: BSD
Platform: any
Classifier: Development Status :: 5 - Production/Stable
Classifier: Intended Audience :: Developers
Classifier: License :: OSI Approved :: BSD License
Classifier: Programming Language :: Python
Classifier: Programming Language :: Python :: 3
Requires-Dist: click
Requires-Dist: more-itertools
Requires-Dist: humanize
Provides-Extra: all
Requires-Dist: jinja2; extra == 'all'
Requires-Dist: watchdog; extra == 'all'
Requires-Dist: htmlmin; extra == 'all'
Provides-Extra: html
Requires-Dist: htmlmin; extra == 'html'
Provides-Extra: jinja2
Requires-Dist: jinja2; extra == 'jinja2'
Provides-Extra: watch
Requires-Dist: watch; extra == 'watch'
